bubot_messenger_bot/__init__.py
bubot_messenger_bot/buject/MessengerBot/Helper.py
bubot_messenger_bot/buject/MessengerBot/MessengerBot.py
bubot_messenger_bot/buject/MessengerBot/MessengerBotApi.py
bubot_messenger_bot/buject/MessengerBot/TelegramBot.py
bubot_messenger_bot/buject/MessengerBot/TelegramBotUpdate.py
bubot_messenger_bot/buject/MessengerBot/TelegramRawApi.py
bubot_messenger_bot/buject/MessengerBot/ViberBot.py
bubot_messenger_bot/buject/MessengerBot/ViberBotUpdate.py
bubot_messenger_bot/buject/MessengerBot/ViberRawApi.py
bubot_messenger_bot/buject/MessengerBot/__init__.py
bubot_messenger_bot/buject/MessengerBotChat/MessengerBotChat.py
bubot_messenger_bot/buject/MessengerBotChat/MessengerBotChatApi.py
bubot_messenger_bot/buject/MessengerBotChat/__init__.py
bubot_messenger_bot/buject/MessengerBotChat/form/Item.form.json
bubot_messenger_bot/buject/MessengerBotChat/form/List.form.json
bubot_messenger_bot/buject/OcfDevice/subtype/MessengerBotUpdater/MessengerBotUpdater.json
bubot_messenger_bot/buject/OcfDevice/subtype/MessengerBotUpdater/MessengerBotUpdater.py
bubot_messenger_bot/buject/OcfDevice/subtype/MessengerBotUpdater/__init__.py
bubot_messenger_bot-4.1.6.dist-info/licenses/LICENSE
bubot_messenger_bot-4.1.6.dist-info/METADATA
bubot_messenger_bot-4.1.6.dist-info/WHEEL
bubot_messenger_bot-4.1.6.dist-info/top_level.txt
bubot_messenger_bot-4.1.6.dist-info/RECORD
