Metadata-Version: 2.4
Name: bubot_messenger_bot
Version: 4.1.6
Home-page: https://gitlab.com/razgovorov/bubot_messenger_bot.git
Author: Razgovorov Mikhail
Author-email: 1338833@gmail.com
Classifier: Programming Language :: Python :: 3
Classifier: Operating System :: OS Independent
Classifier: Framework :: AsyncIO
Requires-Python: >=3.8
License-File: LICENSE
Requires-Dist: bubot_core>=4.1.0
Requires-Dist: bubot_helpers>=4.0.3
Dynamic: author
Dynamic: author-email
Dynamic: classifier
Dynamic: description-content-type
Dynamic: home-page
Dynamic: license-file
Dynamic: requires-dist
Dynamic: requires-python
